{"Source":"InternalBuild","Data":{"System.CollectionId":"41bf5486-7392-4b7a-a7e3-a735c767e3b3","System.DefinitionId":"183390","System.TeamProjectId":"2bdc3060-cc75-4bb4-8e85-9ce981e841fa","System.TeamProject":"D365","Build.BuildId":"74394000","Build.BuildNumber":"23157.2","Build.DefinitionName":"Commerce-Samples-InStore","Build.DefinitionRevision":"74","Build.Repository.Name":"Commerce-Samples-InStore","Build.Repository.Provider":"TfsGit","Build.Repository.Id":"cafed49e-5ca5-4f32-b41b-7a3f833c4d96","Build.SourceBranch":"refs/heads/release/9.41","Build.SourceBranchName":"9.41","Build.SourceVersion":"164710082db22d0badf1adbaedb5fd583e2511de","Build.Repository.Uri":"https://msazure.visualstudio.com/D365/_git/Commerce-Samples-InStore"},"Feed":null}